pyextra/__init__.py
pyextra/py.typed
pyextra/syntax_sugar.py
pyextra/types.py
pyextra-1.0.0.dist-info/LICENSE
pyextra-1.0.0.dist-info/METADATA
pyextra-1.0.0.dist-info/WHEEL
pyextra-1.0.0.dist-info/top_level.txt
pyextra-1.0.0.dist-info/RECORD
